client/__init__.py
client/async_client.py
client/base.py
client/client.py
driver/__init__.py
driver/api_driver.py
driver/async_api_driver.py
driver/base.py
models/__init__.py
models/client.py
models/client_list.py
models/donate.py
models/donate_list.py
models/user.py
models/user_donates.py
donatello-1.0.7.dist-info/LICENSE
donatello-1.0.7.dist-info/METADATA
donatello-1.0.7.dist-info/WHEEL
donatello-1.0.7.dist-info/top_level.txt
donatello-1.0.7.dist-info/RECORD
