Metadata-Version: 2.1
Name: donatello
Version: 1.0.7
Summary: 🐍 Python API wrapper for Ukrainian donate service Donatello
Home-page: https://github.com/selfkilla666/donatello
Download-URL: https://github.com/selfkilla666/donatello/blob/main/dist/donatello-1.0.7.tar.gz
Author: selfkilla666 & Beengoo
Author-email: selfkilla666 <selfkilla666@yahoo.com>, Beengoo <olddft@gmail.com>
License: MIT License (MIT)
Project-URL: Homepage, https://github.com/selfkilla666/donatello/
Classifier: Programming Language :: Python
Classifier: Programming Language :: Python :: 3
Classifier: Programming Language :: Python :: 3.8
Classifier: Programming Language :: Python :: 3.9
Classifier: Programming Language :: Python :: 3.10
Classifier: Programming Language :: Python :: 3.11
Classifier: Operating System :: OS Independent
Requires-Python: >=3.9.0
License-File: LICENSE
Requires-Dist: aiohttp
Requires-Dist: requests
Requires-Dist: pydantic
